<?xml version="1.0" encoding="UTF-8" standalone="yes"?>
<response>
	<header>
		<resultCode>00</resultCode>
		<resultMsg>NORMAL SERVICE.</resultMsg>
	</header>
	<body>
		<items>
			<item>
				<accDefRate>1.4393079615</accDefRate>
				<accExamCnt>9520966</accExamCnt>
				<accExamCompCnt>9403408</accExamCompCnt>
				<careCnt>8386</careCnt>
				<clearCnt>125032</clearCnt>
				<createDt>2021-05-22 09:37:01.885</createDt>
				<deathCnt>1926</deathCnt>
				<decideCnt>135344</decideCnt>
				<examCnt>117558</examCnt>
				<resutlNegCnt>9268064</resutlNegCnt>
				<seq>519</seq><stateDt>20210522</stateDt>
				<stateTime>00:00</stateTime>
				<updateDt>null</updateDt>
			</item>
		</items>
		<numOfRows>10</numOfRows>
		<pageNo>1</pageNo>
		<totalCount>1</totalCount>
	</body></response>
